XivDbReader/Reader.py
XivDbReader/__init__.py
XivDbReader/collections.py
XivDbReader/exceptions.py
XivDbReader/settings.py
XivDbReader/scrape/__init__.py
XivDbReader/scrape/parseDuty.py
XivDbReader/scrape/parseItems.py
XivDbReader/scrape/parseList.py
tests/__init__.py
tests/test_ParseList.py
tests/test_reader.py
tests/items/__init__.py
tests/lists/__init__.py
tests/lists/test_armsLinks.py
XivDbReader-0.0.3.dist-info/LICENSE
XivDbReader-0.0.3.dist-info/METADATA
XivDbReader-0.0.3.dist-info/WHEEL
XivDbReader-0.0.3.dist-info/top_level.txt
XivDbReader-0.0.3.dist-info/RECORD
