Metadata-Version: 2.1
Name: XivDbReader
Version: 0.0.3
Summary: Web scraping package to read the Final Fantasy XIV DB.
Home-page: https://github.com/luther38/XivDbReader
Author: James Tombleson
Author-email: jtombleson38@gmail.com
License: UNKNOWN
Platform: UNKNOWN
Classifier: Programming Language :: Python :: 3
Classifier: License :: OSI Approved :: MIT License
Classifier: Operating System :: OS Independent
Requires-Python: >=3.8
